<annotation>
	<folder>train</folder>
	<filename>IMG_2556.JPG</filename>
	<path>C:\tensorflow_cards\train\IMG_2556.JPG</path>
	<source>
		<database>Unknown</database>
	</source>
	<size>
		<width>378</width>
		<height>504</height>
		<depth>3</depth>
	</size>
	<segmented>0</segmented>
	<object>
		<name>queen</name>
		<pose>Unspecified</pose>
		<truncated>0</truncated>
		<difficult>0</difficult>
		<bndbox>
			<xmin>74</xmin>
			<ymin>195</ymin>
			<xmax>201</xmax>
			<ymax>386</ymax>
		</bndbox>
	</object>
</annotation>
